mcp_server_fetch/__init__.py
mcp_server_fetch/__main__.py
mcp_server_fetch/server.py
mcp_server_fetch-2025.1.16.dist-info/METADATA
mcp_server_fetch-2025.1.16.dist-info/WHEEL
mcp_server_fetch-2025.1.16.dist-info/entry_points.txt
mcp_server_fetch-2025.1.16.dist-info/licenses/LICENSE
mcp_server_fetch-2025.1.16.dist-info/RECORD
